aiire/__init__.py
aiire/agenda.py
aiire/grammar.py
aiire/ontology.py
aiire-2.0.2.dist-info/LICENSE
aiire-2.0.2.dist-info/METADATA
aiire-2.0.2.dist-info/WHEEL
aiire-2.0.2.dist-info/top_level.txt
aiire-2.0.2.dist-info/RECORD
