Metadata-Version: 2.1
Name: aiire
Version: 2.0.2
Summary: AI Information Retrieval Engine
Home-page: http://svn.aiire.org/repos/tproc/trunk/aiire
Author: Alexey Dobrov
Author-email: adobrov@aiire.org
License: LGPLv3
Platform: UNKNOWN
Requires-Python: >=3.6
License-File: LICENSE
Requires-Dist: tqdm
